{
    "11152115": "{\"rating\":4,\"elapsed_days\":137.23114633101852,\"scheduled_days\":365,\"review\":\"20260104111520293\",\"state\":2}",
    "111729922": "{\"rating\":2,\"elapsed_days\":18.059857731481483,\"scheduled_days\":7,\"review\":\"20260104111726238\",\"state\":2}",
    "111800205": "{\"rating\":4,\"elapsed_days\":0,\"scheduled_days\":6,\"review\":\"20260104111747913\",\"state\":0}",
    "112038107": "{\"rating\":4,\"elapsed_days\":0,\"scheduled_days\":6,\"review\":\"20260104112036073\",\"state\":0}",
    "112146127": "{\"rating\":4,\"elapsed_days\":208.0160101388889,\"scheduled_days\":992,\"review\":\"20260104112137596\",\"state\":2}",
    "112157412": "{\"rating\":4,\"elapsed_days\":208.24096679398147,\"scheduled_days\":941,\"review\":\"20260104112146951\",\"state\":2}",
    "112210664": "{\"rating\":4,\"elapsed_days\":0.35551943287037036,\"scheduled_days\":3,\"review\":\"20260104112209335\",\"state\":1}",
    "112400534": "{\"rating\":4,\"elapsed_days\":309.9392878935185,\"scheduled_days\":1481,\"review\":\"20260104112358818\",\"state\":2}",
    "112620517": "{\"rating\":3,\"elapsed_days\":145.2455334490741,\"scheduled_days\":146,\"review\":\"20260104112619534\",\"state\":2}",
    "112622854": "{\"rating\":3,\"elapsed_days\":0,\"scheduled_days\":0,\"review\":\"20260104112621181\",\"state\":0}",
    "112644545": "{\"rating\":3,\"elapsed_days\":146.3267440625,\"scheduled_days\":147,\"review\":\"20260104112626631\",\"state\":2}",
    "113021977": "{\"rating\":3,\"elapsed_days\":0,\"scheduled_days\":0,\"review\":\"20260104113001319\",\"state\":0}",
    "113101701": "{\"rating\":4,\"elapsed_days\":0,\"scheduled_days\":6,\"review\":\"20260104113053391\",\"state\":0}",
    "113104520": "{\"rating\":4,\"elapsed_days\":0,\"scheduled_days\":6,\"review\":\"20260104113102514\",\"state\":0}",
    "113143871": "{\"rating\":4,\"elapsed_days\":363.1985440162037,\"scheduled_days\":1925,\"review\":\"20260104113141867\",\"state\":2}",
    "114055934": "{\"rating\":3,\"elapsed_days\":0,\"scheduled_days\":0,\"review\":\"20260104113603307\",\"state\":0}",
    "024849277": "{\"rating\":4,\"elapsed_days\":0,\"scheduled_days\":6,\"review\":\"20260104024838511\",\"state\":0}",
    "024856550": "{\"rating\":3,\"elapsed_days\":0,\"scheduled_days\":0,\"review\":\"20260104024853705\",\"state\":0}",
    "024904356": "{\"rating\":4,\"elapsed_days\":0,\"scheduled_days\":6,\"review\":\"20260104024859827\",\"state\":0}",
    "024937952": "{\"rating\":4,\"elapsed_days\":0,\"scheduled_days\":6,\"review\":\"20260104024937119\",\"state\":0}",
    "024939761": "{\"rating\":4,\"elapsed_days\":0,\"scheduled_days\":6,\"review\":\"20260104024938779\",\"state\":0}",
    "024959311": "{\"rating\":4,\"elapsed_days\":0,\"scheduled_days\":6,\"review\":\"20260104024942766\",\"state\":0}",
    "025013624": "{\"rating\":3,\"elapsed_days\":0,\"scheduled_days\":0,\"review\":\"20260104025012456\",\"state\":0}",
    "02503918": "{\"rating\":3,\"elapsed_days\":0,\"scheduled_days\":0,\"review\":\"20260104025036574\",\"state\":0}",
    "025045460": "{\"rating\":4,\"elapsed_days\":0,\"scheduled_days\":6,\"review\":\"20260104025042842\",\"state\":0}",
    "02505257": "{\"rating\":2,\"elapsed_days\":0,\"scheduled_days\":0,\"review\":\"20260104025048670\",\"state\":0}",
    "025106364": "{\"rating\":3,\"elapsed_days\":0,\"scheduled_days\":0,\"review\":\"20260104025056604\",\"state\":0}"
}